README.md
setup.py
mediaalpha/__init__.py
mediaalpha/exchange.py
mediaalpha_exchange.egg-info/PKG-INFO
mediaalpha_exchange.egg-info/SOURCES.txt
mediaalpha_exchange.egg-info/dependency_links.txt
mediaalpha_exchange.egg-info/requires.txt
mediaalpha_exchange.egg-info/top_level.txt