Metadata-Version: 2.1
Name: mediaalpha-exchange
Version: 0.0.3
Summary: MediaAlpha Exchange API access.
Home-page: https://github.com/MediaAlpha/mediaalpha-exchange-python/
Author: MediaAlpha Engineering
Author-email: tech@mediaalpha.com
License: UNKNOWN
Platform: UNKNOWN
Classifier: Programming Language :: Python :: 3
Classifier: License :: OSI Approved :: MIT License
